pyclim/__init__.py
pyclim_engine-0.0.1.dist-info/LICENSE
pyclim_engine-0.0.1.dist-info/METADATA
pyclim_engine-0.0.1.dist-info/WHEEL
pyclim_engine-0.0.1.dist-info/top_level.txt
pyclim_engine-0.0.1.dist-info/RECORD
