Metadata-Version: 2.1
Name: pyclim-engine
Version: 0.0.1
Summary: Create CLI-based games.
Home-page: https://github.com/StarlkYT/Pyclim-Engine
Author: StarlkYT
Author-email: starlkytminecraft@gmail.com
License: UNKNOWN
Platform: UNKNOWN
Requires-Python: >=3.7
Requires-Dist: keyboard
Requires-Dist: termcolor
